jieqi/__init__.py
jieqi/cli.py
jieqi/config.py
jieqi/jieqi.py
jieqi/main.py
jieqi-0.1.0.dist-info/AUTHORS.rst
jieqi-0.1.0.dist-info/LICENSE
jieqi-0.1.0.dist-info/METADATA
jieqi-0.1.0.dist-info/WHEEL
jieqi-0.1.0.dist-info/entry_points.txt
jieqi-0.1.0.dist-info/top_level.txt
jieqi-0.1.0.dist-info/RECORD
